instabotnet/__init__.py
instabotnet/__main__.py
instabotnet/assert_good_script.py
instabotnet/direct_inbox_events.py
instabotnet/errors.py
instabotnet/execute.py
instabotnet/handle_errors.py
instabotnet/make_bot.py
instabotnet/make_predicate.py
instabotnet/nodes_edges.py
instabotnet/notification_events.py
instabotnet/populate.py
instabotnet/reducer.py
instabotnet/support.py
instabotnet/__pycache__/__init__.cpython-37.pyc
instabotnet/__pycache__/assert_good_script.cpython-37.pyc
instabotnet/__pycache__/direct_inbox_events.cpython-37.pyc
instabotnet/__pycache__/errors.cpython-37.pyc
instabotnet/__pycache__/execute.cpython-37.pyc
instabotnet/__pycache__/handle_errors.cpython-37.pyc
instabotnet/__pycache__/make_bot.cpython-37.pyc
instabotnet/__pycache__/make_predicate.cpython-37.pyc
instabotnet/__pycache__/nodes_edges.cpython-37.pyc
instabotnet/__pycache__/notification_events.cpython-37.pyc
instabotnet/__pycache__/populate.cpython-37.pyc
instabotnet/__pycache__/reducer.cpython-37.pyc
instabotnet/__pycache__/support.cpython-37.pyc
instabotnet/api/__init__.py
instabotnet/api/api.py
instabotnet/api/__pycache__/__init__.cpython-37.pyc
instabotnet/api/__pycache__/api.cpython-37.pyc
instabotnet/api/instagram_private_api/__init__.py
instabotnet/api/instagram_private_api/client.py
instabotnet/api/instagram_private_api/compat.py
instabotnet/api/instagram_private_api/compatpatch.py
instabotnet/api/instagram_private_api/constants.py
instabotnet/api/instagram_private_api/errors.py
instabotnet/api/instagram_private_api/http.py
instabotnet/api/instagram_private_api/utils.py
instabotnet/api/instagram_private_api/__pycache__/__init__.cpython-37.pyc
instabotnet/api/instagram_private_api/__pycache__/client.cpython-37.pyc
instabotnet/api/instagram_private_api/__pycache__/compat.cpython-37.pyc
instabotnet/api/instagram_private_api/__pycache__/compatpatch.cpython-37.pyc
instabotnet/api/instagram_private_api/__pycache__/constants.cpython-37.pyc
instabotnet-1.0.18.dist-info/LICENSE
instabotnet-1.0.18.dist-info/METADATA
instabotnet-1.0.18.dist-info/WHEEL
instabotnet-1.0.18.dist-info/top_level.txt
instabotnet-1.0.18.dist-info/RECORD
