Metadata-Version: 2.1
Name: instabotnet
Version: 1.0.18
Summary: Instagram readable yaml rpc api for easy instagram scheduling and promotion
Home-page: https://github.com/rpc-botnets/instagram-botnet
Author: Tommaso De Rossi
Author-email: daer.tommy@gmail.com
License: Apache Software License 2.0
Keywords: instagram,bot,api,botnet
Platform: UNKNOWN
Classifier: Intended Audience :: Information Technology
Classifier: License :: OSI Approved :: Apache Software License
Classifier: Programming Language :: Python :: 3
Classifier: Programming Language :: Python :: 3.6
Classifier: Programming Language :: Python :: 3.7
Requires-Dist: pyyaml
Requires-Dist: modeller
Requires-Dist: python-dotenv
Requires-Dist: ffmpeg-python
Requires-Dist: click
Requires-Dist: funcy
Requires-Dist: imagesize
Requires-Dist: colorlog
Requires-Dist: fleep
Requires-Dist: colorama
Requires-Dist: portalocker
